{
    "area_formacion": {
        "pensumId": "100",
        "name": "[OC-4] ORIENTACIÓN Y CONVIVENCIA [pensumId=100]"
    },
    "competencias": [
        {
            "id": "COMP-OC-4-01",
            "referent_id": "1",
            "pensum_id": 100,
            "nombre": "Desarrolla una identidad personal y social coherente, crítica y comprometida con los valores de la Pedagogía Amigoniana.",
            "descripcion": "Reflexiona sobre sus emociones, creencias, roles y pertenencias, integrando principios de solidaridad, responsabilidad, alegría y servicio comunitario."
        },
        {
            "id": "COMP-OC-4-02",
            "referent_id": "1",
            "pensum_id": 100,
            "nombre": "Gestiona sus emociones y conflictos de manera asertiva, empática y no violenta en contextos escolares y comunitarios.",
            "descripcion": "Aplica estrategias de autoconocimiento, regulación emocional y comunicación efectiva para resolver tensiones interpersonales y grupales."
        },
        {
            "id": "COMP-OC-4-03",
            "referent_id": "1",
            "pensum_id": 100,
            "nombre": "Participa activamente en la construcción de ambientes escolares inclusivos, democráticos y libres de violencia.",
            "descripcion": "Promueve el respeto a la diversidad, la equidad de género, los derechos humanos y la convivencia basada en el diálogo y la corresponsabilidad."
        },
        {
            "id": "COMP-OC-4-04",
            "referent_id": "1",
            "pensum_id": 100,
            "nombre": "Ejerce su ciudadanía desde una perspectiva ética, ecológica y comprometida con el bien común.",
            "descripcion": "Actúa con responsabilidad social, defiende el ambiente, participa en decisiones colectivas y se involucra en la transformación de su entorno."
        },
        {
            "id": "COMP-OC-4-05",
            "referent_id": "1",
            "pensum_id": 100,
            "nombre": "Elabora un proyecto de vida personal y profesional con sentido de propósito, realismo y proyección social.",
            "descripcion": "Define metas académicas, laborales y personales alineadas con sus intereses, capacidades y contexto socioeconómico, considerando opciones post-secundarias."
        },
        {
            "id": "COMP-OC-4-06",
            "referent_id": "1",
            "pensum_id": 100,
            "nombre": "Reconoce y valora la diversidad cultural, étnica, religiosa, sexual y de género como riqueza social.",
            "descripcion": "Rechaza toda forma de discriminación, promueve la interculturalidad y defiende los derechos de grupos históricamente marginados."
        },
        {
            "id": "COMP-OC-4-07",
            "referent_id": "1",
            "pensum_id": 100,
            "nombre": "Practica hábitos saludables que fortalecen su bienestar físico, mental y espiritual.",
            "descripcion": "Adopta estilos de vida que incluyen alimentación consciente, actividad física, descanso, higiene mental y uso responsable de tecnologías."
        },
        {
            "id": "COMP-OC-4-08",
            "referent_id": "1",
            "pensum_id": 100,
            "nombre": "Utiliza herramientas digitales de manera crítica, segura y ética en su desarrollo personal y académico.",
            "descripcion": "Navega en internet con conciencia de riesgos, protege su privacidad, evita la desinformación y promueve contenidos positivos y constructivos."
        },
        {
            "id": "COMP-OC-4-09",
            "referent_id": "1",
            "pensum_id": 100,
            "nombre": "Fortalece redes de apoyo afectivo, familiar y comunitario como base de su resiliencia y crecimiento integral.",
            "descripcion": "Identifica figuras de confianza, busca ayuda oportuna y contribuye al bienestar colectivo mediante la escucha activa y la solidaridad."
        },
        {
            "id": "COMP-OC-4-10",
            "referent_id": "1",
            "pensum_id": 100,
            "nombre": "Lidera iniciativas escolares y comunitarias que promueven la paz, la justicia social y la sostenibilidad ambiental.",
            "descripcion": "Organiza campañas, proyectos o colectivos orientados a resolver problemas locales con enfoque participativo, inclusivo y transformador."
        }
    ],
    "indicadores": [
        {
            "id": "IND-OC-4-01-01",
            "competency_id": "COMP-OC-4-01",
            "codigo": "OC-4TO-IL-01",
            "descripcion": "Reflexiona por escrito sobre sus fortalezas, debilidades, valores y aspiraciones personales.",
            "nivel_esperado": 3
        },
        {
            "id": "IND-OC-4-01-02",
            "competency_id": "COMP-OC-4-01",
            "codigo": "OC-4TO-IL-02",
            "descripcion": "Identifica influencias familiares, culturales y mediáticas en la formación de su identidad.",
            "nivel_esperado": 3
        },
        {
            "id": "IND-OC-4-01-03",
            "competency_id": "COMP-OC-4-01",
            "codigo": "OC-4TO-IL-03",
            "descripcion": "Relaciona los principios amigonianos (alegría, trabajo, servicio) con sus decisiones cotidianas.",
            "nivel_esperado": 3
        },
        {
            "id": "IND-OC-4-01-04",
            "competency_id": "COMP-OC-4-01",
            "codigo": "OC-4TO-IL-04",
            "descripcion": "Expresa su identidad a través de producciones creativas (arte, escritura, performance).",
            "nivel_esperado": 3
        },
        {
            "id": "IND-OC-4-01-05",
            "competency_id": "COMP-OC-4-01",
            "codigo": "OC-4TO-IL-05",
            "descripcion": "Reconoce la importancia del sentido de pertenencia a su escuela, comunidad y país.",
            "nivel_esperado": 3
        },
        {
            "id": "IND-OC-4-01-06",
            "competency_id": "COMP-OC-4-01",
            "codigo": "OC-4TO-IL-06",
            "descripcion": "Argumenta por qué la coherencia entre pensamiento, palabra y acción es esencial para la integridad personal.",
            "nivel_esperado": 3
        },
        {
            "id": "IND-OC-4-02-01",
            "competency_id": "COMP-OC-4-02",
            "codigo": "OC-4TO-IL-07",
            "descripcion": "Identifica y nombra sus emociones básicas y complejas en situaciones reales.",
            "nivel_esperado": 3
        },
        {
            "id": "IND-OC-4-02-02",
            "competency_id": "COMP-OC-4-02",
            "codigo": "OC-4TO-IL-08",
            "descripcion": "Aplica técnicas de respiración, pausa o diálogo interno para autorregularse en momentos de estrés.",
            "nivel_esperado": 3
        },
        {
            "id": "IND-OC-4-02-03",
            "competency_id": "COMP-OC-4-02",
            "codigo": "OC-4TO-IL-09",
            "descripcion": "Comunica sus necesidades y límites de forma clara, respetuosa y sin agresividad.",
            "nivel_esperado": 3
        },
        {
            "id": "IND-OC-4-02-04",
            "competency_id": "COMP-OC-4-02",
            "codigo": "OC-4TO-IL-10",
            "descripcion": "Escucha activamente a otros, validando sus emociones y perspectivas.",
            "nivel_esperado": 3
        },
        {
            "id": "IND-OC-4-02-05",
            "competency_id": "COMP-OC-4-02",
            "codigo": "OC-4TO-IL-11",
            "descripcion": "Propone soluciones colaborativas en conflictos grupales sin recurrir a la violencia verbal o física.",
            "nivel_esperado": 3
        },
        {
            "id": "IND-OC-4-02-06",
            "competency_id": "COMP-OC-4-02",
            "codigo": "OC-4TO-IL-12",
            "descripcion": "Participa en círculos restaurativos o mediaciones escolares cuando se requiere.",
            "nivel_esperado": 3
        },
        {
            "id": "IND-OC-4-03-01",
            "competency_id": "COMP-OC-4-03",
            "codigo": "OC-4TO-IL-13",
            "descripcion": "Denuncia actos de bullying, acoso o exclusión en su entorno escolar.",
            "nivel_esperado": 3
        },
        {
            "id": "IND-OC-4-03-02",
            "competency_id": "COMP-OC-4-03",
            "codigo": "OC-4TO-IL-14",
            "descripcion": "Promueve normas de convivencia democráticas elaboradas colectivamente en el aula o la escuela.",
            "nivel_esperado": 3
        },
        {
            "id": "IND-OC-4-03-03",
            "competency_id": "COMP-OC-4-03",
            "codigo": "OC-4TO-IL-15",
            "descripcion": "Incluye activamente a compañeros con discapacidad, migrantes o de minorías en actividades escolares.",
            "nivel_esperado": 3
        },
        {
            "id": "IND-OC-4-03-04",
            "competency_id": "COMP-OC-4-03",
            "codigo": "OC-4TO-IL-16",
            "descripcion": "Cuestiona estereotipos de género, raciales o sociales presentes en el lenguaje o prácticas cotidianas.",
            "nivel_esperado": 3
        },
        {
            "id": "IND-OC-4-03-05",
            "competency_id": "COMP-OC-4-03",
            "codigo": "OC-4TO-IL-17",
            "descripcion": "Participa en consejos estudiantiles o espacios de gobierno escolar con propuestas constructivas.",
            "nivel_esperado": 3
        },
        {
            "id": "IND-OC-4-03-06",
            "competency_id": "COMP-OC-4-03",
            "codigo": "OC-4TO-IL-18",
            "descripcion": "Reconoce que la convivencia pacífica es un derecho y una responsabilidad compartida.",
            "nivel_esperado": 3
        },
        {
            "id": "IND-OC-4-04-01",
            "competency_id": "COMP-OC-4-04",
            "codigo": "OC-4TO-IL-19",
            "descripcion": "Participa en decisiones colectivas respetando reglas democráticas y opiniones diversas.",
            "nivel_esperado": 3
        },
        {
            "id": "IND-OC-4-04-02",
            "competency_id": "COMP-OC-4-04",
            "codigo": "OC-4TO-IL-20",
            "descripcion": "Defiende el cuidado del ambiente como expresión de ciudadanía ecológica.",
            "nivel_esperado": 3
        },
        {
            "id": "IND-OC-4-04-03",
            "competency_id": "COMP-OC-4-04",
            "codigo": "OC-4TO-IL-21",
            "descripcion": "Cumple con sus deberes escolares y comunitarios con responsabilidad y puntualidad.",
            "nivel_esperado": 3
        },
        {
            "id": "IND-OC-4-04-04",
            "competency_id": "COMP-OC-4-04",
            "codigo": "OC-4TO-IL-22",
            "descripcion": "Critica actitudes individualistas y promueve la cooperación como valor social.",
            "nivel_esperado": 3
        },
        {
            "id": "IND-OC-4-04-05",
            "competency_id": "COMP-OC-4-04",
            "codigo": "OC-4TO-IL-23",
            "descripcion": "Se involucra en campañas sociales (salud, educación, justicia) desde su rol estudiantil.",
            "nivel_esperado": 3
        },
        {
            "id": "IND-OC-4-04-06",
            "competency_id": "COMP-OC-4-04",
            "codigo": "OC-4TO-IL-24",
            "descripcion": "Vincula su acción ciudadana con los ODS 16 (Paz, justicia) y 17 (Alianzas).",
            "nivel_esperado": 3
        },
        {
            "id": "IND-OC-4-05-01",
            "competency_id": "COMP-OC-4-05",
            "codigo": "OC-4TO-IL-25",
            "descripcion": "Realiza un autodiagnóstico de intereses, habilidades y áreas de mejora para su futuro.",
            "nivel_esperado": 3
        },
        {
            "id": "IND-OC-4-05-02",
            "competency_id": "COMP-OC-4-05",
            "codigo": "OC-4TO-IL-26",
            "descripcion": "Investiga opciones formativas post-secundarias (universidad, técnico, emprendimiento).",
            "nivel_esperado": 3
        },
        {
            "id": "IND-OC-4-05-03",
            "competency_id": "COMP-OC-4-05",
            "codigo": "OC-4TO-IL-27",
            "descripcion": "Establece metas a corto, mediano y largo plazo con pasos concretos para alcanzarlas.",
            "nivel_esperado": 3
        },
        {
            "id": "IND-OC-4-05-04",
            "competency_id": "COMP-OC-4-05",
            "codigo": "OC-4TO-IL-28",
            "descripcion": "Prepara un currículum vitae básico y practica entrevistas simuladas.",
            "nivel_esperado": 3
        },
        {
            "id": "IND-OC-4-05-05",
            "competency_id": "COMP-OC-4-05",
            "codigo": "OC-4TO-IL-29",
            "descripcion": "Reflexiona sobre cómo su proyecto de vida puede contribuir al desarrollo local y nacional.",
            "nivel_esperado": 3
        },
        {
            "id": "IND-OC-4-05-06",
            "competency_id": "COMP-OC-4-05",
            "codigo": "OC-4TO-IL-30",
            "descripcion": "Presenta su proyecto de vida en un espacio escolar con claridad y coherencia.",
            "nivel_esperado": 3
        },
        {
            "id": "IND-OC-4-06-01",
            "competency_id": "COMP-OC-4-06",
            "codigo": "OC-4TO-IL-31",
            "descripcion": "Reconoce y respeta las distintas formas de expresión de género e identidad sexual.",
            "nivel_esperado": 3
        },
        {
            "id": "IND-OC-4-06-02",
            "competency_id": "COMP-OC-4-06",
            "codigo": "OC-4TO-IL-32",
            "descripcion": "Valora las tradiciones, lenguas y saberes de pueblos indígenas y afrodescendientes.",
            "nivel_esperado": 3
        },
        {
            "id": "IND-OC-4-06-03",
            "competency_id": "COMP-OC-4-06",
            "codigo": "OC-4TO-IL-33",
            "descripcion": "Rechaza chistes, memes o comentarios discriminatorios por origen, religión o condición social.",
            "nivel_esperado": 3
        },
        {
            "id": "IND-OC-4-06-04",
            "competency_id": "COMP-OC-4-06",
            "codigo": "OC-4TO-IL-34",
            "descripcion": "Participa en celebraciones interculturales que promuevan el respeto mutuo.",
            "nivel_esperado": 3
        },
        {
            "id": "IND-OC-4-06-05",
            "competency_id": "COMP-OC-4-06",
            "codigo": "OC-4TO-IL-35",
            "descripcion": "Defiende el derecho a la libre expresión religiosa o filosófica en espacios públicos.",
            "nivel_esperado": 3
        },
        {
            "id": "IND-OC-4-06-06",
            "competency_id": "COMP-OC-4-06",
            "codigo": "OC-4TO-IL-36",
            "descripcion": "Argumenta que la diversidad enriquece la sociedad y fortalece la democracia.",
            "nivel_esperado": 3
        },
        {
            "id": "IND-OC-4-07-01",
            "competency_id": "COMP-OC-4-07",
            "codigo": "OC-4TO-IL-37",
            "descripcion": "Mantiene rutinas de higiene, alimentación balanceada y descanso adecuado.",
            "nivel_esperado": 3
        },
        {
            "id": "IND-OC-4-07-02",
            "competency_id": "COMP-OC-4-07",
            "codigo": "OC-4TO-IL-38",
            "descripcion": "Identifica señales de alerta en su salud mental (ansiedad, aislamiento, tristeza persistente).",
            "nivel_esperado": 3
        },
        {
            "id": "IND-OC-4-07-03",
            "competency_id": "COMP-OC-4-07",
            "codigo": "OC-4TO-IL-39",
            "descripcion": "Evita el consumo de sustancias psicoactivas y reconoce sus riesgos.",
            "nivel_esperado": 3
        },
        {
            "id": "IND-OC-4-07-04",
            "competency_id": "COMP-OC-4-07",
            "codigo": "OC-4TO-IL-40",
            "descripcion": "Practica actividades que fomenten su bienestar espiritual o emocional (meditación, arte, naturaleza).",
            "nivel_esperado": 3
        },
        {
            "id": "IND-OC-4-07-05",
            "competency_id": "COMP-OC-4-07",
            "codigo": "OC-4TO-IL-41",
            "descripcion": "Busca ayuda profesional o de confianza ante dificultades emocionales o psicológicas.",
            "nivel_esperado": 3
        },
        {
            "id": "IND-OC-4-07-06",
            "competency_id": "COMP-OC-4-07",
            "codigo": "OC-4TO-IL-42",
            "descripcion": "Promueve estilos de vida saludables entre sus pares mediante ejemplo o campañas.",
            "nivel_esperado": 3
        },
        {
            "id": "IND-OC-4-08-01",
            "competency_id": "COMP-OC-4-08",
            "codigo": "OC-4TO-IL-43",
            "descripcion": "Configura ajustes de privacidad en redes sociales y plataformas digitales.",
            "nivel_esperado": 3
        },
        {
            "id": "IND-OC-4-08-02",
            "competency_id": "COMP-OC-4-08",
            "codigo": "OC-4TO-IL-44",
            "descripcion": "Verifica la veracidad de información antes de compartirla en línea.",
            "nivel_esperado": 3
        },
        {
            "id": "IND-OC-4-08-03",
            "competency_id": "COMP-OC-4-08",
            "codigo": "OC-4TO-IL-45",
            "descripcion": "Reconoce y evita conductas de ciberacoso, grooming o sexting.",
            "nivel_esperado": 3
        },
        {
            "id": "IND-OC-4-08-04",
            "competency_id": "COMP-OC-4-08",
            "codigo": "OC-4TO-IL-46",
            "descripcion": "Utiliza herramientas digitales para el aprendizaje, la creatividad y la organización personal.",
            "nivel_esperado": 3
        },
        {
            "id": "IND-OC-4-08-05",
            "competency_id": "COMP-OC-4-08",
            "codigo": "OC-4TO-IL-47",
            "descripcion": "Reflexiona sobre el impacto del uso excesivo de pantallas en su salud y relaciones.",
            "nivel_esperado": 3
        },
        {
            "id": "IND-OC-4-08-06",
            "competency_id": "COMP-OC-4-08",
            "codigo": "OC-4TO-IL-48",
            "descripcion": "Promueve una cultura digital responsable, respetuosa y crítica en su entorno.",
            "nivel_esperado": 3
        },
        {
            "id": "IND-OC-4-09-01",
            "competency_id": "COMP-OC-4-09",
            "codigo": "OC-4TO-IL-49",
            "descripcion": "Identifica al menos tres personas de confianza a quienes acudir en situaciones de crisis.",
            "nivel_esperado": 3
        },
        {
            "id": "IND-OC-4-09-02",
            "competency_id": "COMP-OC-4-09",
            "codigo": "OC-4TO-IL-50",
            "descripcion": "Ofrece apoyo emocional a compañeros que atraviesan dificultades.",
            "nivel_esperado": 3
        },
        {
            "id": "IND-OC-4-09-03",
            "competency_id": "COMP-OC-4-09",
            "codigo": "OC-4TO-IL-51",
            "descripcion": "Participa en grupos de pares, clubes o actividades extracurriculares que fortalezcan vínculos.",
            "nivel_esperado": 3
        },
        {
            "id": "IND-OC-4-09-04",
            "competency_id": "COMP-OC-4-09",
            "codigo": "OC-4TO-IL-52",
            "descripcion": "Comunica abiertamente con su familia o tutores sobre sus experiencias y necesidades.",
            "nivel_esperado": 3
        },
        {
            "id": "IND-OC-4-09-05",
            "competency_id": "COMP-OC-4-09",
            "codigo": "OC-4TO-IL-53",
            "descripcion": "Colabora en acciones solidarias dentro de su comunidad (donaciones, voluntariado, acompañamiento).",
            "nivel_esperado": 3
        },
        {
            "id": "IND-OC-4-09-06",
            "competency_id": "COMP-OC-4-09",
            "codigo": "OC-4TO-IL-54",
            "descripcion": "Reconoce que pedir ayuda es un acto de fortaleza, no de debilidad.",
            "nivel_esperado": 3
        },
        {
            "id": "IND-OC-4-10-01",
            "competency_id": "COMP-OC-4-10",
            "codigo": "OC-4TO-IL-55",
            "descripcion": "Identifica un problema social o ambiental en su entorno escolar o comunitario.",
            "nivel_esperado": 3
        },
        {
            "id": "IND-OC-4-10-02",
            "competency_id": "COMP-OC-4-10",
            "codigo": "OC-4TO-IL-56",
            "descripcion": "Diseña una iniciativa colectiva (campaña, taller, proyecto) para abordarlo.",
            "nivel_esperado": 3
        },
        {
            "id": "IND-OC-4-10-03",
            "competency_id": "COMP-OC-4-10",
            "codigo": "OC-4TO-IL-57",
            "descripcion": "Moviliza recursos, aliados y participantes para ejecutar su propuesta.",
            "nivel_esperado": 3
        },
        {
            "id": "IND-OC-4-10-04",
            "competency_id": "COMP-OC-4-10",
            "codigo": "OC-4TO-IL-58",
            "descripcion": "Evalúa el impacto de su iniciativa en términos de conciencia, cambio de prácticas o bienestar colectivo.",
            "nivel_esperado": 3
        },
        {
            "id": "IND-OC-4-10-05",
            "competency_id": "COMP-OC-4-10",
            "codigo": "OC-4TO-IL-59",
            "descripcion": "Documenta y comunica los resultados de su liderazgo comunitario.",
            "nivel_esperado": 3
        },
        {
            "id": "IND-OC-4-10-06",
            "competency_id": "COMP-OC-4-10",
            "codigo": "OC-4TO-IL-60",
            "descripcion": "Inspira a otros jóvenes a asumir roles protagónicos en la transformación social.",
            "nivel_esperado": 3
        }
    ]
}